telegram_markdown_text/__init__.py
telegram_markdown_text/markdown_text.py
telegram_markdown_text-0.5.0.dist-info/METADATA
telegram_markdown_text-0.5.0.dist-info/WHEEL
telegram_markdown_text-0.5.0.dist-info/top_level.txt
telegram_markdown_text-0.5.0.dist-info/RECORD
