Metadata-Version: 2.1
Name: telegram-markdown-text
Version: 0.5.0
Summary: Simple MarkdownV2 string builder for the Telegram API
Home-page: https://github.com/mrvayzard/telegram-markdown-text
Author: Denys Yablonskyi
Keywords: telegram,tg,markdown,markdownV2,text
